<?xml version="1.0" encoding="utf-8"?>
<!DOCTYPE hibernate-mapping PUBLIC "-//Hibernate/Hibernate Mapping DTD 3.0//EN" "http://www.hibernate.org/dtd/hibernate-mapping-3.0.dtd"[]>
<hibernate-mapping package="org.dddml.suiinfinitesea.domain.itemproduction">
  <class name="org.dddml.suiinfinitesea.domain.itemproduction.AbstractItemProductionState$SimpleItemProductionState" table="item_production">
    <composite-id name="itemProductionId" class="org.dddml.suiinfinitesea.domain.SkillTypeItemIdPair">
      <key-property name="skillType">
        <column name="item_production_id_skill_type" />
      </key-property>
      <key-property name="itemId">
        <column name="item_production_id_item_id" />
      </key-property>
    </composite-id>
    <version name="offChainVersion" column="off_chain_version" type="long" />
    <property name="id_">
      <column name="id" unique-key="unique_itemproduction_sid" sql-type="VARCHAR(66)" />
    </property>
    <property name="productionMaterials">
      <column name="production_materials" sql-type="json" />
      <type name="io.hypersistence.utils.hibernate.type.json.JsonType">
        <param name="org.hibernate.type.ParameterType">java.util.HashMap</param>
      </type>
    </property>
    <property name="requirementsLevel">
      <column name="requirements_level" />
    </property>
    <property name="baseQuantity">
      <column name="base_quantity" />
    </property>
    <property name="baseExperience">
      <column name="base_experience" />
    </property>
    <property name="baseCreationTime">
      <column name="base_creation_time" sql-type="DECIMAL(20,0)" />
    </property>
    <property name="energyCost">
      <column name="energy_cost" sql-type="DECIMAL(20,0)" />
    </property>
    <property name="successRate">
      <column name="success_rate" />
    </property>
    <property name="version">
      <column name="version" sql-type="DECIMAL(20,0)" />
    </property>
    <property name="createdBy">
      <column name="created_by" />
    </property>
    <property name="updatedBy">
      <column name="updated_by" />
    </property>
    <property name="active">
      <column name="active" />
    </property>
    <property name="deleted">
      <column name="deleted" />
    </property>
    <property name="createdAt" column="created_at" />
    <property name="updatedAt" column="updated_at" />
  </class>
</hibernate-mapping>
